{
  "contacts": [
    {
      "id": 1,
      "name": "Harry",
      "lastName": "Potter",
      "about": "Lorem ipsum dolor sit amet, consectetur adipiscing elit"
    },
    {
      "id": 2,
      "name": "Luke",
      "lastName": "Skywalker",
      "about": "Lorem ipsum dolor sit amet, consectetur adipiscing elit"
    },
    {
      "name": "Lucy",
      "lastName": "Grey",
      "about": "Lorem ipsum dolor sit amet, consectetur adipiscing elit",
      "id": 3
    },
    {
      "name": "Lucy",
      "lastName": "Grey",
      "about": "Lorem ipsum dolor sit amet, consectetur adipiscing elit",
      "id": 4
    },
    {
      "name": "Lucy",
      "lastName": "Grey",
      "about": "Lorem ipsum dolor sit amet, consectetur adipiscing elit",
      "id": 5
    },
    {
      "name": "Lucy",
      "lastName": "Grey",
      "about": "Lorem ipsum dolor sit amet, consectetur adipiscing elit",
      "id": 6
    },
    {
      "name": "Lucy",
      "lastName": "Grey",
      "about": "Lorem ipsum dolor sit amet, consectetur adipiscing elit",
      "id": 7
    },
    {
      "name": "Lucy",
      "lastName": "Grey",
      "about": "Lorem ipsum dolor sit amet, consectetur adipiscing elit",
      "id": 8
    },
    {
      "name": "Lucy",
      "lastName": "Grey",
      "about": "Lorem ipsum dolor sit amet, consectetur adipiscing elit",
      "id": 9
    },
    {
      "name": "Lucy",
      "lastName": "Grey",
      "about": "Lorem ipsum dolor sit amet, consectetur adipiscing elit",
      "id": 10
    },
    {
      "name": "Lucy",
      "lastName": "Grey",
      "about": "Lorem ipsum dolor sit amet, consectetur adipiscing elit",
      "id": 11
    },
    {
      "name": "Lucy",
      "lastName": "Grey",
      "about": "Lorem ipsum dolor sit amet, consectetur adipiscing elit",
      "id": 12
    },
    {
      "name": "Lucy",
      "lastName": "Grey",
      "about": "Lorem ipsum dolor sit amet, consectetur adipiscing elit",
      "id": 13
    },
    {
      "name": "Lucy",
      "lastName": "Grey",
      "about": "Lorem ipsum dolor sit amet, consectetur adipiscing elit",
      "id": 14
    },
    {
      "name": "Lucy",
      "lastName": "Grey",
      "about": "Lorem ipsum dolor sit amet, consectetur adipiscing elit",
      "id": 15
    },
    {
      "name": "Lucy",
      "lastName": "Grey",
      "about": "Lorem ipsum dolor sit amet, consectetur adipiscing elit",
      "id": 16
    }
  ]
}